{
  "agendas": [
    {
      "id": "1",
      "title": "Prova do Glauco",
      "description": "Prova do Glauco vai cair java",
      "date_hora": "2024-12-02 08:00:00",
      "local": "lab 6"
    },
    {
      "id": "2",
      "title": "Prova de estatistica",
      "description": "Prova do chico ",
      "date_hora": "2024-12-01 08:00:00",
      "local": "lab 4"
    },
    {
      "id": "3",
      "title": "Entrega do trabalho",
      "description": "Entrega do trabalho de engenharia de software 2",
      "date_hora": "2024-12-05 08:00:00",
      "local": "lab 3"
    },
    {
      "id": "",
      "title": "Trabalho sobre agenda",
      "description": "Testar o trabalho na AWS",
      "date_hora": "2024-12-10",
      "local": "Lab. 6"
    },
    {
      "id": "",
      "title": "Apresentação de inglês",
      "description": "Apresentar o objetivo em inglês",
      "date_hora": "2024-12-11",
      "local": "Sala 8"
    },
    {
      "id": "",
      "title": "Teste",
      "description": "teste",
      "date_hora": "2024-12-12",
      "local": "teste"
    }
  ]
}